LICENSE
MANIFEST.in
README.md
setup.py
../LICENSE
../README.md
hopsml/__init__.py
hopsml/connection.py
hopsml/constants.py
hopsml/decorators.py
hopsml/model.py
hopsml/model_registry.py
hopsml/tag.py
hopsml/util.py
hopsml/version.py
hopsml.egg-info/PKG-INFO
hopsml.egg-info/SOURCES.txt
hopsml.egg-info/dependency_links.txt
hopsml.egg-info/requires.txt
hopsml.egg-info/top_level.txt
hopsml/client/__init__.py
hopsml/client/auth.py
hopsml/client/base.py
hopsml/client/exceptions.py
hopsml/client/external.py
hopsml/client/hopsworks.py
hopsml/core/__init__.py
hopsml/core/dataset_api.py
hopsml/core/model_api.py
hopsml/core/model_registry_api.py
hopsml/core/native_hdfs_api.py
hopsml/engine/__init__.py
hopsml/engine/hopsworks_engine.py
hopsml/engine/local_engine.py
hopsml/engine/model_engine.py
hopsml/python/__init__.py
hopsml/python/model.py
hopsml/python/signature.py
hopsml/sklearn/__init__.py
hopsml/sklearn/model.py
hopsml/sklearn/signature.py
hopsml/tensorflow/__init__.py
hopsml/tensorflow/model.py
hopsml/tensorflow/signature.py
hopsml/torch/__init__.py
hopsml/torch/model.py
hopsml/torch/signature.py
hopsml/utils/__init__.py
hopsml/utils/column.py
hopsml/utils/columnar_schema.py
hopsml/utils/model_schema.py
hopsml/utils/schema.py
hopsml/utils/tensor.py
hopsml/utils/tensor_schema.py
tests/__init__.py
tests/hsml/__init__.py
tests/hsml/core/__init__.py